command_line_tools.py
auth_get_sso_cookie/__init__.py
auth_get_sso_cookie/cern_sso.py
auth_get_sso_cookie/old_cern_sso.py
auth_get_sso_cookie/test_cern_sso.py
auth_get_sso_cookie-2.2.0.dist-info/METADATA
auth_get_sso_cookie-2.2.0.dist-info/WHEEL
auth_get_sso_cookie-2.2.0.dist-info/entry_points.txt
auth_get_sso_cookie-2.2.0.dist-info/top_level.txt
auth_get_sso_cookie-2.2.0.dist-info/RECORD
