Metadata-Version: 2.1
Name: auth-get-sso-cookie
Version: 2.2.0
Summary: Utility for aquiring CERN Single Sign-On cookie using Kerberos credentials.
Home-page: https://gitlab.cern.ch/authzsvc/docs/auth-get-sso-cookie
Author: Asier Aguado
Author-email: asier.aguado@cern.ch
License: MIT
Keywords: authentication sso cern
Classifier: Development Status :: 3 - Alpha
Classifier: Intended Audience :: Developers
Classifier: License :: OSI Approved :: MIT License
Classifier: Programming Language :: Python :: 3
Requires-Dist: requests
Requires-Dist: requests-gssapi
Requires-Dist: beautifulsoup4
